phasespace/__init__.py
phasespace/backend.py
phasespace/kinematics.py
phasespace/phasespace.py
phasespace/random.py
phasespace/fromdecay/__init__.py
phasespace/fromdecay/genmultidecay.py
phasespace/fromdecay/mass_functions.py
tests/__init__.py
tests/conftest.py
tests/test_chain.py
tests/test_generate.py
tests/test_nbody_decay.py
tests/test_physics.py
tests/test_random.py
tests/fromdecay/__init__.py
tests/fromdecay/example_decay_chains.py
tests/fromdecay/example_decays.dec
tests/fromdecay/test_fromdecay.py
tests/fromdecay/test_mass_functions.py
tests/helpers/__init__.py
tests/helpers/decays.py
tests/helpers/plotting.py
tests/helpers/rapidsim.py
phasespace-1.10.3.dist-info/LICENSE
phasespace-1.10.3.dist-info/METADATA
phasespace-1.10.3.dist-info/WHEEL
phasespace-1.10.3.dist-info/top_level.txt
phasespace-1.10.3.dist-info/RECORD
