Metadata-Version: 2.1
Name: phasespace
Version: 1.10.3
Summary: TensorFlow implementation of the Raubold and Lynch method for n-body events
Home-page: https://github.com/zfit/phasespace
Author: Albert Puig Navarro
Author-email: apuignav@gmail.com
Maintainer: zfit
Maintainer-email: zfit@physik.uzh.ch
License: BSD-3-Clause
Keywords: TensorFlow,phasespace,HEP
Classifier: Development Status :: 5 - Production/Stable
Classifier: Intended Audience :: Science/Research
Classifier: License :: OSI Approved :: BSD License
Classifier: Natural Language :: English
Classifier: Operating System :: MacOS
Classifier: Operating System :: Unix
Classifier: Programming Language :: Python :: 3
Classifier: Programming Language :: Python :: 3 :: Only
Classifier: Programming Language :: Python :: 3.9
Classifier: Programming Language :: Python :: 3.10
Classifier: Programming Language :: Python :: 3.11
Classifier: Programming Language :: Python :: 3.12
Classifier: Topic :: Scientific/Engineering :: Physics
Requires-Python: >=3.9
License-File: LICENSE
Requires-Dist: tensorflow >=2.16.0
Requires-Dist: tensorflow-probability >=0.22.0
Provides-Extra: dev
Requires-Dist: particle >=0.16.0 ; extra == 'dev'
Requires-Dist: zfit >=0.12.0 ; extra == 'dev'
Requires-Dist: zfit-physics >=0.6 ; extra == 'dev'
Requires-Dist: decaylanguage >=0.12.0 ; extra == 'dev'
Requires-Dist: vector >=1.0.0 ; extra == 'dev'
Requires-Dist: graphviz ; extra == 'dev'
Requires-Dist: Sphinx ; extra == 'dev'
Requires-Dist: myst-nb ; extra == 'dev'
Requires-Dist: sphinx-bootstrap-theme ; extra == 'dev'
Requires-Dist: jupyter-sphinx ; extra == 'dev'
Requires-Dist: sphinx-math-dollar ; extra == 'dev'
Requires-Dist: awkward <2.0,>=1.0 ; extra == 'dev'
Requires-Dist: coverage ; extra == 'dev'
Requires-Dist: flaky ; extra == 'dev'
Requires-Dist: matplotlib ; extra == 'dev'
Requires-Dist: nbval ; extra == 'dev'
Requires-Dist: numpy ; extra == 'dev'
Requires-Dist: pytest ; extra == 'dev'
Requires-Dist: pytest-cov ; extra == 'dev'
Requires-Dist: pytest-xdist ; extra == 'dev'
Requires-Dist: scipy ; extra == 'dev'
Requires-Dist: uproot <5.0,>=4.0 ; extra == 'dev'
Requires-Dist: wget ; extra == 'dev'
Requires-Dist: bumpversion ; extra == 'dev'
Requires-Dist: pre-commit ; extra == 'dev'
Requires-Dist: twine ; extra == 'dev'
Requires-Dist: watchdog ; extra == 'dev'
Provides-Extra: doc
Requires-Dist: particle >=0.16.0 ; extra == 'doc'
Requires-Dist: zfit >=0.12.0 ; extra == 'doc'
Requires-Dist: zfit-physics >=0.6 ; extra == 'doc'
Requires-Dist: decaylanguage >=0.12.0 ; extra == 'doc'
Requires-Dist: vector >=1.0.0 ; extra == 'doc'
Requires-Dist: graphviz ; extra == 'doc'
Requires-Dist: Sphinx ; extra == 'doc'
Requires-Dist: myst-nb ; extra == 'doc'
Requires-Dist: sphinx-bootstrap-theme ; extra == 'doc'
Requires-Dist: jupyter-sphinx ; extra == 'doc'
Requires-Dist: sphinx-math-dollar ; extra == 'doc'
Provides-Extra: fromdecay
Requires-Dist: particle >=0.16.0 ; extra == 'fromdecay'
Requires-Dist: zfit >=0.12.0 ; extra == 'fromdecay'
Requires-Dist: zfit-physics >=0.6 ; extra == 'fromdecay'
Requires-Dist: decaylanguage >=0.12.0 ; extra == 'fromdecay'
Provides-Extra: tensorflow
Requires-Dist: tensorflow ; extra == 'tensorflow'
Requires-Dist: tensorflow-probability ; extra == 'tensorflow'
Provides-Extra: test
Requires-Dist: particle >=0.16.0 ; extra == 'test'
Requires-Dist: zfit >=0.12.0 ; extra == 'test'
Requires-Dist: zfit-physics >=0.6 ; extra == 'test'
Requires-Dist: decaylanguage >=0.12.0 ; extra == 'test'
Requires-Dist: vector >=1.0.0 ; extra == 'test'
Requires-Dist: awkward <2.0,>=1.0 ; extra == 'test'
Requires-Dist: coverage ; extra == 'test'
Requires-Dist: flaky ; extra == 'test'
Requires-Dist: matplotlib ; extra == 'test'
Requires-Dist: nbval ; extra == 'test'
Requires-Dist: numpy ; extra == 'test'
Requires-Dist: pytest ; extra == 'test'
Requires-Dist: pytest-cov ; extra == 'test'
Requires-Dist: pytest-xdist ; extra == 'test'
Requires-Dist: scipy ; extra == 'test'
Requires-Dist: uproot <5.0,>=4.0 ; extra == 'test'
Requires-Dist: wget ; extra == 'test'
Provides-Extra: tf
Requires-Dist: tensorflow ; extra == 'tf'
Requires-Dist: tensorflow-probability ; extra == 'tf'
Provides-Extra: vector
Requires-Dist: vector >=1.0.0 ; extra == 'vector'
